pyawful/__init__.py
pyawful/awful_client.py
pyawful/errors.py
pyawful/network_client.py
pyawful/py.typed
pyawful/types.py
pyawful/models/__init__.py
pyawful/models/forum.py
pyawful/models/post.py
pyawful/models/post_list.py
pyawful/models/profile.py
pyawful/models/thread.py
pyawful/models/thread_list.py
pyawful/models/user.py
pyawful/parse/__init__.py
pyawful/parse/common.py
pyawful/parse/error_parser.py
pyawful/parse/forum_parser.py
pyawful/parse/profile_parser.py
pyawful/parse/thread_parser.py
pyawful-0.5.0.dist-info/METADATA
pyawful-0.5.0.dist-info/WHEEL
pyawful-0.5.0.dist-info/RECORD
