Metadata-Version: 2.3
Name: pyawful
Version: 0.5.0
Summary: Pay ten dollars to get access to a dead forum.
Requires-Python: >=3.12
Requires-Dist: cssselect>=1.2.0
Requires-Dist: lxml>=5.3.0
Requires-Dist: requests>=2.32.3
